Utilize-1.0.1.dist-info/DESCRIPTION.rst
Utilize-1.0.1.dist-info/METADATA
Utilize-1.0.1.dist-info/RECORD
Utilize-1.0.1.dist-info/WHEEL
Utilize-1.0.1.dist-info/metadata.json
Utilize-1.0.1.dist-info/top_level.txt
utilize/__init__.py
utilize/__main__.py
